{
  "version": "1",
  "metadata": {
    "marimo_version": "0.22.0",
    "script_metadata_hash": null
  },
  "cells": [
    {
      "id": "setup",
      "code_hash": "0dcbd77cc661128d379a91d7c5ed1042",
      "outputs": [
        {
          "type": "data",
          "data": {
            "text/plain": ""
          }
        }
      ],
      "console": []
    },
    {
      "id": "Hbol",
      "code_hash": "e6d664b5e31ac1d7e1b20bcb6a396ec1",
      "outputs": [
        {
          "type": "data",
          "data": {
            "text/plain": ""
          }
        }
      ],
      "console": []
    },
    {
      "id": "MJUe",
      "code_hash": "8ebace03c40afd105dff752bda471b1a",
      "outputs": [
        {
          "type": "data",
          "data": {
            "text/plain": ""
          }
        }
      ],
      "console": []
    },
    {
      "id": "vblA",
      "code_hash": "651c636cffdda82eb97c5f80a205b14e",
      "outputs": [
        {
          "type": "data",
          "data": {
            "text/plain": ""
          }
        }
      ],
      "console": []
    },
    {
      "id": "bkHC",
      "code_hash": null,
      "outputs": [],
      "console": []
    }
  ]
}